tnnt_templates/__init__.py
tnnt_templates/app_settings.py
tnnt_templates/apps.py
tnnt_templates/checks.py
tnnt_templates/context_processors.py
tnnt_templates/providers.py
tnnt_templates/images/tnnt-template.jpg
tnnt_templates/management/commands/tnnt_anonymize_emails.py
tnnt_templates/static/tnnt_templates/favicons/README.md
tnnt_templates/static/tnnt_templates/favicons/android-chrome-144x144.png
tnnt_templates/static/tnnt_templates/favicons/android-chrome-192x192.png
tnnt_templates/static/tnnt_templates/favicons/android-chrome-256x256.png
tnnt_templates/static/tnnt_templates/favicons/android-chrome-36x36.png
tnnt_templates/static/tnnt_templates/favicons/android-chrome-48x48.png
tnnt_templates/static/tnnt_templates/favicons/android-chrome-72x72.png
tnnt_templates/static/tnnt_templates/favicons/android-chrome-96x96.png
tnnt_templates/static/tnnt_templates/favicons/apple-touch-icon-114x114-precomposed.png
tnnt_templates/static/tnnt_templates/favicons/apple-touch-icon-114x114.png
tnnt_templates/static/tnnt_templates/favicons/apple-touch-icon-120x120-precomposed.png
tnnt_templates/static/tnnt_templates/favicons/apple-touch-icon-120x120.png
tnnt_templates/static/tnnt_templates/favicons/apple-touch-icon-144x144-precomposed.png
tnnt_templates/static/tnnt_templates/favicons/apple-touch-icon-144x144.png
tnnt_templates/static/tnnt_templates/favicons/apple-touch-icon-152x152-precomposed.png
tnnt_templates/static/tnnt_templates/favicons/apple-touch-icon-152x152.png
tnnt_templates/static/tnnt_templates/favicons/apple-touch-icon-180x180-precomposed.png
tnnt_templates/static/tnnt_templates/favicons/apple-touch-icon-180x180.png
tnnt_templates/static/tnnt_templates/favicons/apple-touch-icon-57x57-precomposed.png
tnnt_templates/static/tnnt_templates/favicons/apple-touch-icon-57x57.png
tnnt_templates/static/tnnt_templates/favicons/apple-touch-icon-60x60-precomposed.png
tnnt_templates/static/tnnt_templates/favicons/apple-touch-icon-60x60.png
tnnt_templates-3.14.1.dist-info/METADATA
tnnt_templates-3.14.1.dist-info/WHEEL
tnnt_templates-3.14.1.dist-info/licenses/LICENSE
tnnt_templates-3.14.1.dist-info/RECORD
