Metadata-Version: 2.4
Name: tnnt-templates
Version: 3.14.1
Summary: Terra Nanotech Template Overrides for Alliance Auth
Project-URL: Changelog, https://github.com/terra-nanotech/tn-nt-auth-templates/blob/master/CHANGELOG.md
Project-URL: Codecov, https://codecov.io/gh/terra-nanotech/tn-nt-auth-templates
Project-URL: Documentation, https://github.com/terra-nanotech/tn-nt-auth-templates/blob/master/README.md
Project-URL: GitHub, https://github.com/terra-nanotech/tn-nt-auth-templates
Author-email: Peter Pfeufer <develop@ppfeufer.de>
License:                     GNU GENERAL PUBLIC LICENSE
License-File: LICENSE
Keywords: allianceauth,eveonline,template,template_override,terra_nanotech
Classifier: Environment :: Web Environment
Classifier: Framework :: Django
Classifier: Framework :: Django :: 4.2
Classifier: Intended Audience :: Developers
Classifier: License :: OSI Approved :: GNU General Public License v3 (GPLv3)
Classifier: Operating System :: OS Independent
Classifier: Programming Language :: Python
Classifier: Programming Language :: Python :: 3 :: Only
Classifier: Programming Language :: Python :: 3.10
Classifier: Programming Language :: Python :: 3.11
Classifier: Programming Language :: Python :: 3.12
Classifier: Programming Language :: Python :: 3.13
Classifier: Topic :: Internet :: WWW/HTTP
Classifier: Topic :: Internet :: WWW/HTTP :: Dynamic Content
Requires-Python: <3.14,>=3.10
Requires-Dist: allianceauth<5,>=4.10
Provides-Extra: tests-allianceauth-latest
Requires-Dist: aa-gdpr; extra == 'tests-allianceauth-latest'
Requires-Dist: coverage; extra == 'tests-allianceauth-latest'
Requires-Dist: django-webtest; extra == 'tests-allianceauth-latest'
